sinetstreamplugin/kafka.py
sinetstream_kafka-1.9.2.dist-info/METADATA
sinetstream_kafka-1.9.2.dist-info/WHEEL
sinetstream_kafka-1.9.2.dist-info/entry_points.txt
sinetstream_kafka-1.9.2.dist-info/RECORD
